pyemailval.py
pyemailval-0.55555.dist-info/METADATA
pyemailval-0.55555.dist-info/RECORD
pyemailval-0.55555.dist-info/WHEEL
pyemailval-0.55555.dist-info/top_level.txt
