Metadata-Version: 2.1
Name: pyemailval
Version: 0.55555
Summary: pyemailval verifies if an email address really exists.
Home-page: http://github.com/ben-baert/pyemailval
Author: Ben Baert
Author-email: ben_b@gmx.com
License: LGPL
Download-URL: http://github.com/ben-baert/pyemailval/archive/0.1.tar.gz
Keywords: email validation verification mx verify
Platform: UNKNOWN
